hyperpocket_llamaindex/__init__.py
hyperpocket_llamaindex/pocket_llamaindex.py
hyperpocket_llamaindex-0.5.7.dist-info/METADATA
hyperpocket_llamaindex-0.5.7.dist-info/WHEEL
hyperpocket_llamaindex-0.5.7.dist-info/RECORD
