Metadata-Version: 2.4
Name: hyperpocket-llamaindex
Version: 0.5.7
Author-email: Hyperpocket Team <hyperpocket@vessl.ai>
Requires-Python: >=3.10
Requires-Dist: hyperpocket>=0.0.3
Requires-Dist: llama-index>=0.10.10
